Metadata-Version: 1.1
Name: micropython-am2320
Version: 1.0.0
Summary: MicroPython library for the AM2320 temperature and humidity sensor.
Home-page: https://github.com/mcauser/micropython-am2320
Author: Mike Causer
Author-email: mcauser@gmail.com
License: MIT
Keywords: am2320 aosong dht temperature humidity micropython
Platform: UNKNOWN
Classifier: Development Status :: 5 - Production/Stable
Classifier: Programming Language :: Python :: Implementation :: MicroPython
Classifier: License :: OSI Approved :: MIT License
